web_grepy/cli.py
web_grepy-1.1.0.dist-info/entry_points.txt
web_grepy-1.1.0.dist-info/LICENSE
web_grepy-1.1.0.dist-info/WHEEL
web_grepy-1.1.0.dist-info/METADATA
web_grepy-1.1.0.dist-info/RECORD
