Metadata-Version: 2.1
Name: web-grepy
Version: 1.1.0
Summary: web-grep written in Python3
Home-page: https://github.com/cympfh/web-grepy/
License: MIT
Author: cympfh
Author-email: cympfh@gmail.com
Requires-Python: >=3.9,<4.0
Classifier: License :: OSI Approved :: MIT License
Classifier: Programming Language :: Python :: 3
Classifier: Programming Language :: Python :: 3.10
Classifier: Programming Language :: Python :: 3.9
Requires-Dist: click (>=8.0.4,<9.0.0)
Requires-Dist: easy-scraper-py (>=1.0.0,<2.0.0)
Project-URL: Repository, https://github.com/cympfh/web-grepy/
